mistrs/__init__.py
mistrs/api.py
mistrs/auth.py
mistrs/data.py
mistrs/net.py
mistrs-0.1.7.dist-info/licenses/LICENSE
mistrs-0.1.7.dist-info/METADATA
mistrs-0.1.7.dist-info/WHEEL
mistrs-0.1.7.dist-info/top_level.txt
mistrs-0.1.7.dist-info/RECORD
