Metadata-Version: 2.4
Name: mistrs
Version: 0.1.7
Summary: A collection of basic functions to communicate with Mist API
Home-page: https://github.com/rstandage/mistrs
Author: Rory Standage
License: MIT License
Classifier: Development Status :: 3 - Alpha
Classifier: Intended Audience :: Developers
Classifier: License :: OSI Approved :: MIT License
Classifier: Operating System :: OS Independent
Classifier: Programming Language :: Python :: 3
Classifier: Programming Language :: Python :: 3.6
Classifier: Programming Language :: Python :: 3.7
Classifier: Programming Language :: Python :: 3.8
Classifier: Programming Language :: Python :: 3.9
Requires-Python: >=3.6
License-File: LICENSE
Requires-Dist: pandas<=2.2.3
Requires-Dist: prettytable<=3.14.0
Requires-Dist: requests>=2.25.0
Requires-Dist: urllib3>=1.26.0
Requires-Dist: tqdm>=4.67.1
Requires-Dist: matplotlib>=3.10.3
Requires-Dist: seaborn>=0.13.2
Dynamic: author
Dynamic: classifier
Dynamic: home-page
Dynamic: license
Dynamic: license-file
Dynamic: requires-dist
Dynamic: requires-python
Dynamic: summary
